taiconvert/__init__.py
taiconvert/__main__.py
taiconvert/cli.py
taiconvert/utils.py
taiconvert/commands/__init__.py
taiconvert/commands/convert.py
taiconvert/commands/extract.py
taiconvert-0.2.1.dist-info/LICENSE
taiconvert-0.2.1.dist-info/METADATA
taiconvert-0.2.1.dist-info/WHEEL
taiconvert-0.2.1.dist-info/entry_points.txt
taiconvert-0.2.1.dist-info/top_level.txt
taiconvert-0.2.1.dist-info/RECORD
