Metadata-Version: 2.1
Name: taiconvert
Version: 0.2.1
Summary: This CLI can be used to easily convert TavernAI character \images to JSON for the different pygmalion Web-UIs.
Home-page: https://github.com/Mindus1/taiconvert
Author: Mindus
License: MIT License
Project-URL: Issues, https://github.com/Mindus1/taiconvert/issues
Project-URL: CI, https://github.com/Mindus1/taiconvert/actions
Project-URL: Changelog, https://github.com/Mindus1/taiconvert/releases
Requires-Python: >=3.10
License-File: LICENSE
Requires-Dist: click
Requires-Dist: pillow
Provides-Extra: dev
Requires-Dist: black ; extra == 'dev'
Requires-Dist: flake8 ; extra == 'dev'
Requires-Dist: autopep8 ; extra == 'dev'
Requires-Dist: pre-commit ; extra == 'dev'
Requires-Dist: pyinstaller ; extra == 'dev'
